{
   "ContextClassName": "SalesInfoContext",
   "ContextNamespace": null,
   "DefaultDacpacSchema": null,
   "DoNotCombineNamespace": false,
   "IdReplace": false,
   "IncludeConnectionString": false,
   "ModelNamespace": null,
   "OutputContextPath": "Classes\/SalesDbContext",
   "OutputPath": "Models",
   "ProjectRootNamespace": "SalesInfoService.DataAccess",
   "SelectedHandlebarsLanguage": 0,
   "SelectedToBeGenerated": 0,
   "Tables": [
      {
         "HasPrimaryKey": true,
         "Name": "[dbo].[Client]"
      },
      {
         "HasPrimaryKey": true,
         "Name": "[dbo].[Manager]"
      },
      {
         "HasPrimaryKey": true,
         "Name": "[dbo].[Product]"
      },
      {
         "HasPrimaryKey": true,
         "Name": "[dbo].[Sale]"
      }
   ],
   "UseDatabaseNames": false,
   "UseFluentApiOnly": true,
   "UseHandleBars": false,
   "UseInflector": true,
   "UseLegacyPluralizer": false,
   "UseSpatial": false
}